{"features":[{"geometry":{"coordinates":[-8.73937,42.21210],"type":"Point"},"type":"Feature","properties":{"barrio":"VIGO","codigo_postal":"36210","numero":0,"web":null,"calle":"RUA VAL MIÑOR","parroquia":"VIGO","lon":-8.73937,"id":536,"telefono":"986233102","nombre":"Bombeiros (Parque Auxiliar de Balaídos)","lat":42.21210}},{"geometry":{"coordinates":[-8.68649,42.24921],"type":"Point"},"type":"Feature","properties":{"barrio":"PARAIXAL","codigo_postal":"36216","numero":46,"web":null,"calle":"RUA ANGEL DE LEMA Y MARINA","parroquia":"TEIS","lon":-8.68649,"id":537,"telefono":"080","nombre":"Bombeiros (Parque Central de Teis)","lat":42.24921}}],"type":"FeatureCollection"}